crystalmaths/__init__.py
crystalmaths/angles_from_fft.py
crystalmaths/angles_from_structure_data.py
crystalmaths/compile_results.py
crystalmaths/distance_from_fft.py
crystalmaths/file_download.py
crystalmaths/find_matching_angles.py
crystalmaths/get_d.py
crystalmaths/google_authorization.py
crystalmaths/imagetools.py
crystalmaths/setup.py
crystalmaths/trans_mode.py
crystalmaths/version.py
crystalmaths-0.0.0.dist-info/LICENSE
crystalmaths-0.0.0.dist-info/METADATA
crystalmaths-0.0.0.dist-info/WHEEL
crystalmaths-0.0.0.dist-info/top_level.txt
crystalmaths-0.0.0.dist-info/RECORD
