Metadata-Version: 2.1
Name: crystalmaths
Version: 0.0.0
Summary: Package for indexing the zone axis of a high res TEM image
Home-page: https://github.com/crystalmaths/crystalmaths
Author: Amy Stegmann, Edwin Shenjian Jiang, Elena Shoushpanova,              Kacper Lachowski
License: MIT
Platform: UNKNOWN
Requires-Python: >=3.7
